{
  "employees": [
    {
      "id": 1,
      "Name": "Dio"
    },
    {
      "id": 2,
      "Name": "Deska"
    },
    {
      "id": 3,
      "Name": "Weweh"
    },
    {
      "id": 4,
      "Name": "Blehbleh"
    },
    {
      "id": 5,
      "Name": "wowwow"
    },
    {
      "id": "8a85",
      "Name": "slkjfalskjdf"
    },
    {
      "id": "7064",
      "Name": "beo"
    },
    {
      "id": "5273",
      "Name": "asddf"
    },
    {
      "id": "1011",
      "Name": "ddf"
    },
    {
      "id": "f528",
      "Name": "Network Error"
    },
    {
      "id": "a373",
      "Name": "jhgjhgjh"
    },
    {
      "id": "7266",
      "Name": "sddf"
    },
    {
      "id": "9953",
      "Name": "odi"
    },
    {
      "id": "4720",
      "Name": "beben"
    },
    {
      "id": "040b",
      "Name": "sdkfj"
    }
  ],
  "products": [],
  "todos": []
}